{"name":"ARQ16","slug_name":"arq16","extra":"","author":"ENDESGA","description":"","like_count":111,"comment_count":0,"hashtag":"arq16","color_count":16,"download_count":2478,"colors":["ffffff","ffd19d","aeb5bd","4d80c9","e93841","100820","511e43","054494","f1892d","823e2c","ffa9a9","5ae150","ffe947","7d3ebf","eb6c82","1e8a4c"],"preview_images":["https://cdn.lospec.com/palette-examples/arq16-palette-example-palette-map-by-chris-wearly-5b099d.png","https://cdn.lospec.com/palette-examples/arq16-palette-example-by-hector-gonzalez-5ffa92.png"],"tags":["artist","endesga"]}