{"name":"Violet Voyage","slug_name":"violet-voyage","extra":"","author":"joe70098","description":"Colors ranging from purple to yellow-orange are good for a cosmic setting.","like_count":130,"comment_count":2,"hashtag":"violetvoyage","color_count":9,"download_count":1286,"colors":["0a0a28","1d0f3f","351567","501f9a","8b2ddc","ff45e9","ff89b4","feabab","ffc5a0"],"preview_images":["https://cdn.lospec.com/palette-examples/violet-voyage-palette-example-by-joe70098-526114.png"],"tags":["violet","pink","orange","cosmic"]}